encryptedcode/L0123.py
encryptedcode/__init__.py
encryptedcode-1.1.10.dist-info/METADATA
encryptedcode-1.1.10.dist-info/WHEEL
encryptedcode-1.1.10.dist-info/top_level.txt
encryptedcode-1.1.10.dist-info/RECORD
