Metadata-Version: 2.1
Name: encryptedcode
Version: 1.1.10
Summary: This library can be used to encrypt and decrypt passwords using the new L0123 algorithm.
Home-page: https://github.com/leoGlez01/encypted-code
Author: Ing. Leandro Gonzalez Espinosa
Author-email: lworkgonzalez01@gmail.com
License: MIT
Keywords: encode,decode,algorithm,cryptography,Leandro Gonzalez Espinosa,Leandro Gonzalez,Glez Dev
Classifier: Programming Language :: Python :: 3
Classifier: License :: OSI Approved :: MIT License
Classifier: Operating System :: OS Independent
Requires-Python: >=3.6
Requires-Dist: cryptography >=3.4.7
